WindowsExploitKaifaJiaochengMassimilianoTomassoli/README.md
WindowsExploitKaifaJiaochengMassimilianoTomassoli/__init__.py
WindowsExploitKaifaJiaochengMassimilianoTomassoli/__main__.py
WindowsExploitKaifaJiaochengMassimilianoTomassoli/file.epub
WindowsExploitKaifaJiaochengMassimilianoTomassoli/index.html
WindowsExploitKaifaJiaochengMassimilianoTomassoli/css/__init__.py
WindowsExploitKaifaJiaochengMassimilianoTomassoli/css/annotations.css
WindowsExploitKaifaJiaochengMassimilianoTomassoli/css/main.css
WindowsExploitKaifaJiaochengMassimilianoTomassoli/css/normalize.css
WindowsExploitKaifaJiaochengMassimilianoTomassoli/css/popup.css
WindowsExploitKaifaJiaochengMassimilianoTomassoli/font/__init__.py
WindowsExploitKaifaJiaochengMassimilianoTomassoli/font/fontello.eot
WindowsExploitKaifaJiaochengMassimilianoTomassoli/font/fontello.svg
WindowsExploitKaifaJiaochengMassimilianoTomassoli/font/fontello.ttf
WindowsExploitKaifaJiaochengMassimilianoTomassoli/font/fontello.woff
WindowsExploitKaifaJiaochengMassimilianoTomassoli/img/__init__.py
WindowsExploitKaifaJiaochengMassimilianoTomassoli/img/annotator-glyph-sprite.png
WindowsExploitKaifaJiaochengMassimilianoTomassoli/img/annotator-icon-sprite.png
WindowsExploitKaifaJiaochengMassimilianoTomassoli/img/apple-touch-icon.png
WindowsExploitKaifaJiaochengMassimilianoTomassoli/img/cancelfullscreen.png
WindowsExploitKaifaJiaochengMassimilianoTomassoli/img/close.png
WindowsExploitKaifaJiaochengMassimilianoTomassoli/img/fullscreen.png
WindowsExploitKaifaJiaochengMassimilianoTomassoli/img/loader.gif
WindowsExploitKaifaJiaochengMassimilianoTomassoli/img/menu-icon.png
WindowsExploitKaifaJiaochengMassimilianoTomassoli/img/save.png
WindowsExploitKaifaJiaochengMassimilianoTomassoli/img/saved.png
WindowsExploitKaifaJiaochengMassimilianoTomassoli/img/settings-s.png
WindowsExploitKaifaJiaochengMassimilianoTomassoli/img/settings.png
WindowsExploitKaifaJiaochengMassimilianoTomassoli/img/star.png
windows_exploit_kaifa_jiaocheng_massimiliano_tomassoli-2024.3.2.0.dist-info/METADATA
windows_exploit_kaifa_jiaocheng_massimiliano_tomassoli-2024.3.2.0.dist-info/WHEEL
windows_exploit_kaifa_jiaocheng_massimiliano_tomassoli-2024.3.2.0.dist-info/entry_points.txt
windows_exploit_kaifa_jiaocheng_massimiliano_tomassoli-2024.3.2.0.dist-info/top_level.txt
windows_exploit_kaifa_jiaocheng_massimiliano_tomassoli-2024.3.2.0.dist-info/RECORD
